firefox_code_coverage/__init__.py
firefox_code_coverage/codecoverage.py
tests/__init__.py
tests/test.py
firefox_code_coverage-1.3.32.dist-info/METADATA
firefox_code_coverage-1.3.32.dist-info/WHEEL
firefox_code_coverage-1.3.32.dist-info/entry_points.txt
firefox_code_coverage-1.3.32.dist-info/top_level.txt
firefox_code_coverage-1.3.32.dist-info/RECORD
