Metadata-Version: 2.1
Name: firefox-code-coverage
Version: 1.3.32
Summary: Code Coverage Report generator for Firefox
Home-page: https://github.com/mozilla/code-coverage
Author: Mozilla Release Management Analysis (sallt)
Author-email: release-mgmt-analysis@mozilla.com
License: MPL2
Requires-Dist: python-magic ==0.4.27
Requires-Dist: taskcluster ==67.1.0
Requires-Dist: tenacity ==8.5.0
Requires-Dist: zstandard ==0.23.0
